verify_email/__init__.py
verify_email/fast_verify.py
verify_email/verify_email.py
verify_email/tests/__init__.py
verify_email/tests/test_verify_email.py
verify_email-2.4.3.dist-info/LICENSE
verify_email-2.4.3.dist-info/METADATA
verify_email-2.4.3.dist-info/WHEEL
verify_email-2.4.3.dist-info/top_level.txt
verify_email-2.4.3.dist-info/RECORD
