Metadata-Version: 2.1
Name: verify_email
Version: 2.4.3
Summary: A small package for email verification
Home-page: https://github.com/kakshay21/verify_email
Author: Kumar Akshay
Author-email: k.akshay9721@gmail.com
License: UNKNOWN
Platform: UNKNOWN
Classifier: Programming Language :: Python :: 3.7
Classifier: License :: OSI Approved :: MIT License
Classifier: Operating System :: OS Independent
